Workbook

Sheet Dashboard
B2: NOIZY LABS — Financial Operations Command Center
B3: Fish Music Inc | acct_1S7kf5B1WYNnCLY0 | Generated: 2026-03-25
B5: KEY METRICS
B7: Metric | C7: Current | D7: Prior Month | E7: Change | F7: % Change
B8: Monthly Recurring Revenue (MRR) | C8: ='Revenue Tracking'!G2 -> 0 | E8: =IF(D8=0,"—",C8-D8) -> — | F8: =IF(D8=0,"—",(C8-D8)/D8) -> —
B9: Annual Run Rate (ARR) | C9: ='Revenue Tracking'!G2*12 -> 0 | E9: =IF(D9=0,"—",C9-D9) -> — | F9: =IF(D9=0,"—",(C9-D9)/D9) -> —
B10: Active Licensees | C10: ='Revenue Tracking'!G3 -> 0 | E10: =IF(D10=0,"—",C10-D10) -> — | F10: =IF(D10=0,"—",(C10-D10)/D10) -> —
B11: Artist Royalty Pool (75%) | C11: ='Revenue Tracking'!G2*0.75 -> 0 | E11: =IF(D11=0,"—",C11-D11) -> — | F11: =IF(D11=0,"—",(C11-D11)/D11) -> —
B12: NOIZY Platform Fee (25%) | C12: ='Revenue Tracking'!G2*0.25 -> 0 | E12: =IF(D12=0,"—",C12-D12) -> — | F12: =IF(D12=0,"—",(C12-D12)/D12) -> —
B13: Founding Members (85/15) | C13: ='Revenue Tracking'!G4 -> NOIZY Revenue | E13: =IF(D13=0,"—",C13-D13) -> — | F13: =IF(D13=0,"—",(C13-D13)/D13) -> —
B16: INFRASTRUCTURE STATUS
B18: System | C18: Status | D18: Details
B19: Heaven17 Consent Kernel | C19: LIVE | D19: heaven17.noizylab.workers.dev
B20: gabriel_db (D1) | C20: LIVE | D20: 10 consent tables, 68 total
B21: Stripe Payments | C21: LIVE | D21: 4 products, 4 prices, 4 payment links
B22: Consent Gateway Worker | C22: DEPLOY READY | D22: 515 lines, wrangler.toml configured
B23: R2 Voice Vault | C23: BLOCKED | D23: Requires Dashboard enablement
B24: noizy.ai Landing | C24: BUILT | D24: Awaiting wrangler deploy
B25: DreamChamber | C25: LOCAL | D25: Port 7777, 11 providers
B26: Linear Project Tracking | C26: LIVE | D26: 11 issues, critical path tracked
B27: GABRIEL Memory Graph | C27: LIVE | D27: 40+ entities, 60+ relations
B29: CRITICAL PATH → APRIL 17, 2026
B31: Issue | C31: Block | D31: Due Date | E31: Priority | F31: Status
B32: NOI-18 | C32: BLOCK 0: GoDaddy Exit | D32: 2026-03-28 | E32: URGENT | F32: Manual — CF email change
B33: NOI-19 | C33: BLOCK 1: Deploy consent-gateway | D33: 2026-03-29 | E33: URGENT | F33: wrangler deploy on GOD.local
B34: NOI-20 | C34: BLOCK 2: Enable R2 storage | D34: 2026-03-30 | E34: HIGH | F34: Manual — CF Dashboard
B35: NOI-21 | C35: BLOCK 3: Fix ANTHROPIC_API_KEY | D35: 2026-03-31 | E35: HIGH | F35: New API key needed
B36: NOI-22 | C36: BLOCK 4: CF API token | D36: 2026-04-01 | E36: HIGH | F36: Scoped token creation
B37: NOI-23 | C37: BLOCK 5: GitHub consolidation | D37: 2026-04-05 | E37: MEDIUM | F37: Repo organization
B38: NOI-26 | C38: Castle briefing email | D38: 2026-04-01 | E38: HIGH | F38: Drafted — send manually

Sheet Chart of Accounts
A1: NOIZY Labs / Fish Music Inc — Chart of Accounts
A3: Account # | B3: Account Name | C3: Type | D3: Category | E3: Description
A4: 1000 | B4: Cash — Operating | C4: Asset | D4: Current | E4: Primary business checking (Stripe payouts)
A5: 1010 | B5: Cash — Stripe Balance | C5: Asset | D5: Current | E5: Funds held in Stripe pending payout
A6: 1020 | B6: Cash — Reserve | C6: Asset | D6: Current | E6: Operating reserve / emergency fund
A7: 1100 | B7: Accounts Receivable | C7: Asset | D7: Current | E7: Licensee invoices outstanding
A8: 1200 | B8: Prepaid Expenses | C8: Asset | D8: Current | E8: Prepaid hosting, domains, subscriptions
A9: 1300 | B9: Security Deposits | C9: Asset | D9: Current | E9: Service deposits
A10: 1500 | B10: Equipment — M2 Ultra | C10: Asset | D10: Fixed | E10: GOD.local Mac Studio
A11: 1510 | B11: Accumulated Depreciation | C11: Asset | D11: Fixed | E11: Contra-asset for equipment
A12: 1600 | B12: Intangible Assets — Software | C12: Asset | D12: Intangible | E12: Developed software (Heaven17, DreamChamber)
A13: 1610 | B13: Intangible Assets — Voice DNA Vault | C13: Asset | D13: Intangible | E13: Enrolled voice recordings and spectral data
A14: 2000 | B14: Accounts Payable | C14: Liability | D14: Current | E14: Vendor invoices owed
... A51: 8100 | B51: Tax Credits — SR&ED | C51: Tax | D51: Tax | E51: Canadian SR&ED R&D tax credits

Sheet Revenue Tracking
A1: NOIZY Revenue & Licensee Tracking
F2: Total MRR: | G2: =SUMPRODUCT(B5:B8,C5:C8) -> 0
F3: Total Licensees: | G3: =SUM(B5:B8) -> 0
A4: Tier | B4: Active Licensees | C4: Price/Mo | D4: Monthly Rev | E4: Artist Split | F4: Artist Payout | G4: NOIZY Revenue
A5: Community/Indie | B5: 0 | C5: 29.99 | D5: =B5*C5 -> 0 | E5: 0.75 | F5: =D5*E5 -> 0 | G5: =D5-F5 -> 0
A6: Standard Commercial | B6: 0 | C6: 149.99 | D6: =B6*C6 -> 0 | E6: 0.75 | F6: =D6*E6 -> 0 | G6: =D6-F6 -> 0
A7: Premium/Broadcast | B7: 0 | C7: 499.99 | D7: =B7*C7 -> 0 | E7: 0.75 | F7: =D7*E7 -> 0 | G7: =D7-F7 -> 0
A8: Founding Member | B8: 0 | C8: 99.99 | D8: =B8*C8 -> 0 | E8: 0.85 | F8: =D8*E8 -> 0 | G8: =D8-F8 -> 0
A9: TOTAL | B9: =SUM(B5:B8) -> 0 | D9: =SUM(D5:D8) -> 0 | F9: =SUM(F5:F8) -> 0 | G9: =SUM(G5:G8) -> 0
A11: MONTHLY REVENUE LEDGER
A12: Month | B12: Community | C12: Standard | D12: Premium | E12: Founding | F12: Total MRR | G12: Artist Payouts | H12: NOIZY Net | I12: Cumulative
A13: Apr-26 | F13: =SUM(B13:E13) -> 0 | G13: =(B13+C13+D13)*0.75+E13*0.85 -> 0 | H13: =F13-G13 -> 0 | I13: =H13 -> 0
A14: May-26 | F14: =SUM(B14:E14) -> 0 | G14: =(B14+C14+D14)*0.75+E14*0.85 -> 0 | H14: =F14-G14 -> 0 | I14: =I13+H14 -> 0
A15: Jun-26 | F15: =SUM(B15:E15) -> 0 | G15: =(B15+C15+D15)*0.75+E15*0.85 -> 0 | H15: =F15-G15 -> 0 | I15: =I14+H15 -> 0
A16: Jul-26 | F16: =SUM(B16:E16) -> 0 | G16: =(B16+C16+D16)*0.75+E16*0.85 -> 0 | H16: =F16-G16 -> 0 | I16: =I15+H16 -> 0
A17: Aug-26 | F17: =SUM(B17:E17) -> 0 | G17: =(B17+C17+D17)*0.75+E17*0.85 -> 0 | H17: =F17-G17 -> 0 | I17: =I16+H17 -> 0
A18: Sep-26 | F18: =SUM(B18:E18) -> 0 | G18: =(B18+C18+D18)*0.75+E18*0.85 -> 0 | H18: =F18-G18 -> 0 | I18: =I17+H18 -> 0
A19: Oct-26 | F19: =SUM(B19:E19) -> 0 | G19: =(B19+C19+D19)*0.75+E19*0.85 -> 0 | H19: =F19-G19 -> 0 | I19: =I18+H19 -> 0
A20: Nov-26 | F20: =SUM(B20:E20) -> 0 | G20: =(B20+C20+D20)*0.75+E20*0.85 -> 0 | H20: =F20-G20 -> 0 | I20: =I19+H20 -> 0
A21: Dec-26 | F21: =SUM(B21:E21) -> 0 | G21: =(B21+C21+D21)*0.75+E21*0.85 -> 0 | H21: =F21-G21 -> 0 | I21: =I20+H21 -> 0
A22: Jan-27 | F22: =SUM(B22:E22) -> 0 | G22: =(B22+C22+D22)*0.75+E22*0.85 -> 0 | H22: =F22-G22 -> 0 | I22: =I21+H22 -> 0
A23: Feb-27 | F23: =SUM(B23:E23) -> 0 | G23: =(B23+C23+D23)*0.75+E23*0.85 -> 0 | H23: =F23-G23 -> 0 | I23: =I22+H23 -> 0
A24: Mar-27 | F24: =SUM(B24:E24) -> 0 | G24: =(B24+C24+D24)*0.75+E24*0.85 -> 0 | H24: =F24-G24 -> 0 | I24: =I23+H24 -> 0

Sheet Stripe Reconciliation
A1: Stripe Revenue Reconciliation
A2: Reconcile Stripe payouts to GL cash and revenue accounts monthly
A4: Period | B4: Stripe Gross | C4: Stripe Fees | D4: Stripe Net | E4: GL Revenue | F4: GL Cash | G4: Variance
A5: Apr-26 | G5: =D5-F5 -> 0
A6: May-26 | G6: =D6-F6 -> 0
A7: Jun-26 | G7: =D7-F7 -> 0
A8: Jul-26 | G8: =D8-F8 -> 0
A9: Aug-26 | G9: =D9-F9 -> 0
A10: Sep-26 | G10: =D10-F10 -> 0
A11: Oct-26 | G11: =D11-F11 -> 0
A12: Nov-26 | G12: =D12-F12 -> 0
A13: Dec-26 | G13: =D13-F13 -> 0
A14: Jan-27 | G14: =D14-F14 -> 0
A15: Feb-27 | G15: =D15-F15 -> 0
A16: Mar-27 | G16: =D16-F16 -> 0
A19: RECONCILING ITEMS
A20: Date | B20: Description | C20: Amount | D20: Category | E20: Status | F20: Resolution

Sheet Royalty Accounting
A1: Artist Royalty Accounting & Payout Tracker
A2: 75/25 standard split | 85/15 founding | All amounts USD | Kill Switch = instant freeze
A4: Actor ID | B4: Actor Name | C4: Tier | D4: Gross Revenue | E4: Split % | F4: Royalty Owed | G4: Paid to Date | H4: Balance Due
A5: RSP_001 | B5: Robert Stephen Plowman | C5: Founding | D5: 0 | E5: 0.85 | F5: =D5*E5 -> 0 | G5: 0 | H5: =F5-G5 -> 0
F6: =IF(D6="","",D6*E6) | H6: =IF(F6="","",F6-G6)
F7: =IF(D7="","",D7*E7) | H7: =IF(F7="","",F7-G7)
F8: =IF(D8="","",D8*E8) | H8: =IF(F8="","",F8-G8)
F9: =IF(D9="","",D9*E9) | H9: =IF(F9="","",F9-G9)
F10: =IF(D10="","",D10*E10) | H10: =IF(F10="","",F10-G10)
F11: =IF(D11="","",D11*E11) | H11: =IF(F11="","",F11-G11)
F12: =IF(D12="","",D12*E12) | H12: =IF(F12="","",F12-G12)
F13: =IF(D13="","",D13*E13) | H13: =IF(F13="","",F13-G13)
F14: =IF(D14="","",D14*E14) | H14: =IF(F14="","",F14-G14)
F15: =IF(D15="","",D15*E15) | H15: =IF(F15="","",F15-G15)
F16: =IF(D16="","",D16*E16) | H16: =IF(F16="","",F16-G16)
F17: =IF(D17="","",D17*E17) | H17: =IF(F17="","",F17-G17)
... F24: =IF(D24="","",D24*E24) | H24: =IF(F24="","",F24-G24)
A25: TOTAL | D25: =SUM(D5:D24) -> 0 | F25: =SUM(F5:F24) -> 0 | G25: =SUM(G5:G24) -> 0 | H25: =SUM(H5:H24) -> 0

Sheet Pro Forma P&L
A1: NOIZY Labs — Pro Forma Income Statement
A2: Year 1 Projection (April 2026 — March 2027) | All amounts USD
B4: Q1 (Apr-Jun) | C4: Q2 (Jul-Sep) | D4: Q3 (Oct-Dec) | E4: Q4 (Jan-Mar) | F4: Full Year
A5: REVENUE
A6: License Revenue — Community/Indie | B6: 90 | C6: 300 | D6: 750 | E6: 1500 | F6: =SUM(B6:E6) -> 2640
A7: License Revenue — Standard Commercial | B7: 0 | C7: 450 | D7: 1500 | E7: 3000 | F7: =SUM(B7:E7) -> 4950
A8: License Revenue — Premium/Broadcast | B8: 0 | C8: 0 | D8: 1500 | E8: 3000 | F8: =SUM(B8:E8) -> 4500
A9: License Revenue — Founding Member | B9: 300 | C9: 500 | D9: 700 | E9: 900 | F9: =SUM(B9:E9) -> 2400
A10: Total Revenue | B10: =SUM(B6:B9) -> 390 | C10: =SUM(C6:C9) -> 1250 | D10: =SUM(D6:D9) -> 4450 | E10: =SUM(E6:E9) -> 8400 | F10: =SUM(F6:F9) -> 14490
A12: COST OF REVENUE
A13: Cloudflare Hosting | B13: 25 | C13: 50 | D13: 100 | E13: 200 | F13: =SUM(B13:E13) -> 375
A14: AI Provider Costs | B14: 50 | C14: 100 | D14: 200 | E14: 400 | F14: =SUM(B14:E14) -> 750
A15: Stripe Processing Fees | B15: =B10*0.029 -> 11.31 | C15: =C10*0.029 -> 36.25 | D15: =D10*0.029 -> 129.05 | E15: =E10*0.029 -> 243.6 | F15: =F10*0.029 -> 420.21
A16: Artist Royalty Payouts | B16: =B10*0.77 -> 300.3 | C16: =C10*0.77 -> 962.5 | D16: =D10*0.77 -> 3426.5 | E16: =E10*0.77 -> 6468 | F16: =F10*0.77 -> 11157.3
A17: C2PA / Provenance | B17: 10 | C17: 20 | D17: 40 | E17: 75 | F17: =SUM(B17:E17) -> 145
A18: Total Cost of Revenue | B18: =SUM(B13:B17) -> 396.61 | C18: =SUM(C13:C17) -> 1168.75 | D18: =SUM(D13:D17) -> 3895.55 | E18: =SUM(E13:E17) -> 7386.6 | F18: =SUM(F13:F17) -> 12847.51
A20: GROSS PROFIT | B20: =B10-B18 -> -6.61 | C20: =C10-C18 -> 81.25 | D20: =D10-D18 -> 554.45 | E20: =E10-E18 -> 1013.4 | F20: =F10-F18 -> 1642.49
A21: Gross Margin % | B21: =IF(B10=0,0,B20/B10) -> -0.016948718 | C21: =IF(C10=0,0,C20/C10) -> 0.065 | D21: =IF(D10=0,0,D20/D10) -> 0.12459551 | E21: =IF(E10=0,0,E20/E10) -> 0.12064286 | F21: =IF(F10=0,0,F20/F10) -> 0.11335335
A23: OPERATING EXPENSES
A24: Domain Registrations | B24: 40 | C24: 10 | D24: 10 | E24: 10 | F24: =SUM(B24:E24) -> 70
A25: Software Subscriptions | B25: 100 | C25: 120 | D25: 150 | E25: 180 | F25: =SUM(B25:E25) -> 550
A26: Professional Services (Legal) | B26: 500 | C26: 500 | D26: 750 | E26: 1000 | F26: =SUM(B26:E26) -> 2750
A27: Marketing & Communications | B27: 100 | C27: 200 | D27: 400 | E27: 600 | F27: =SUM(B27:E27) -> 1300
A28: Insurance | B28: 75 | C28: 75 | D28: 75 | E28: 75 | F28: =SUM(B28:E28) -> 300
A29: General & Administrative | B29: 50 | C29: 75 | D29: 100 | E29: 125 | F29: =SUM(B29:E29) -> 350
A30: Total Operating Expenses | B30: =SUM(B24:B29) -> 865 | C30: =SUM(C24:C29) -> 980 | D30: =SUM(D24:D29) -> 1485 | E30: =SUM(E24:E29) -> 1990 | F30: =SUM(F24:F29) -> 5320
A32: OPERATING INCOME (LOSS) | B32: =B20-B30 -> -871.61 | C32: =C20-C30 -> -898.75 | D32: =D20-D30 -> -930.55 | E32: =E20-E30 -> -976.6 | F32: =F20-F30 -> -3677.51
A34: SR&ED Tax Credit (estimated) | B34: =B24*0.15 -> 6 | C34: =C24*0.15 -> 1.5 | D34: =D24*0.15 -> 1.5 | E34: =E24*0.15 -> 1.5 | F34: =F24*0.15 -> 10.5
A35: NET INCOME (LOSS) | B35: =B32+B34 -> -865.61 | C35: =C32+C34 -> -897.25 | D35: =D32+D34 -> -929.05 | E35: =E32+E34 -> -975.1 | F35: =F32+F34 -> -3667.01

Sheet Month-End Close
A1: NOIZY Labs — Month-End Close Checklist
A3: Day | B3: Task | C3: Owner | D3: Status | E3: Due Date | F3: Notes
A4: T+0 | B4: Confirm Stripe payout for month processed | C4: RSP_001 | F4: Download Stripe balance report
A5: T+0 | B5: Export Stripe transaction CSV for period | C5: RSP_001 | F5: Stripe Dashboard → Reports
A6: T+0 | B6: Confirm all subscription renewals processed | C6: RSP_001 | F6: Check for failed payments
A7: T+1 | B7: Reconcile Stripe payouts to bank deposits | C7: RSP_001 | F7: Use Stripe Reconciliation sheet
A8: T+1 | B8: Record revenue by license tier (4 accounts) | C8: RSP_001 | F8: Accts 4000-4030
A9: T+1 | B9: Calculate and record royalty obligations | C9: RSP_001 | F9: 75/25 standard, 85/15 founding
A10: T+1 | B10: Record Stripe processing fees (5200) | C10: RSP_001 | F10: ~2.9% + $0.30/txn
A11: T+1 | B11: Record Cloudflare hosting costs (5000-5020) | C11: RSP_001 | F11: CF Dashboard → Billing
A12: T+1 | B12: Record AI provider costs (5100) | C12: RSP_001 | F12: Anthropic, OpenAI invoices
A13: T+2 | B13: Record software subscription expenses (6110) | C13: RSP_001 | F13: GitHub, Linear, Slack, etc.
A14: T+2 | B14: Review and post accruals | C14: RSP_001 | F14: Any unpaid invoices
A15: T+2 | B15: Update prepaid expense amortization | C15: RSP_001 | F15: Domains, annual subscriptions
... A23: T+4 | B23: Post to NOIZY Ledger (append-only) | C23: RSP_001 | F23: gabriel_db audit_log entry

Sheet Stripe Products
A1: Stripe Product & Price Registry
A2: Account: Fish Music Inc (acct_1S7kf5B1WYNnCLY0) | LIVE MODE | Updated: 2026-03-25
A4: Tier | B4: Product ID | C4: Price/Mo | D4: Price ID | E4: Payment Link ID | F4: Payment URL
A5: Community/Indie | B5: prod_UDTtsVWchlImmS | C5: 29.99 | D5: price_1TF36xB1WYNnCLY0RXEMKabo | E5: plink_1TF379B1WYNnCLY0ls1IBxV2 | F5: https://buy.stripe.com/3cI4gy0DWbSJ3PV3LT6EU00
A6: Standard Commercial | B6: prod_UDTtVemnNMq7JU | C6: 149.99 | D6: price_1TF36yB1WYNnCLY0WrNLwut7 | E6: plink_1TF37AB1WYNnCLY0cxOXnoKC | F6: https://buy.stripe.com/4gM4gyfyQ1e5fyD3LT6EU01
A7: Premium/Broadcast | B7: prod_UDTt1tF6qOHe0y | C7: 499.99 | D7: price_1TF36zB1WYNnCLY0I7UQTuLs | E7: plink_1TF37BB1WYNnCLY0Y3NQVo6H | F7: https://buy.stripe.com/28E9ASaew4qh5Y30zH6EU02
A8: Founding Member | B8: prod_UDTtI62buomJzn | C8: 99.99 | D8: price_1TF370B1WYNnCLY0oCB8uIla | E8: plink_1TF37CB1WYNnCLY02cBD3Gf7 | F8: https://buy.stripe.com/cNi8wO5Yg3md3PV8296EU03
A10: Royalty Split Structure
A11: Tier | B11: Artist % | C11: NOIZY % | D11: Notes
A12: Community/Indie | B12: 0.75 | C12: 0.25 | D12: Non-commercial, indie creators
A13: Standard Commercial | B13: 0.75 | C13: 0.25 | D13: SAG-AFTRA/ACTRA compliant
A14: Premium/Broadcast | B14: 0.75 | C14: 0.25 | D14: Custom terms, exclusivity options
A15: Founding Member | B15: 0.85 | C15: 0.15 | D15: First 100 actors — lifetime rate
